aider_sdk.py
aider_sdk-0.1.0.dist-info/METADATA
aider_sdk-0.1.0.dist-info/WHEEL
aider_sdk-0.1.0.dist-info/top_level.txt
aider_sdk-0.1.0.dist-info/RECORD
