Metadata-Version: 2.4
Name: aider-sdk
Version: 0.1.0
Summary: A simple Python SDK for using Aider programmatically
Author: Sean Sullivan
Author-email: RVCa <rvca212@gmail.com>
License: MIT
Project-URL: Homepage, https://github.com/rvca212/aider-sdk
Project-URL: Bug Tracker, https://github.com/rvca212/aider-sdk/issues
Requires-Python: >=3.10
Requires-Dist: aider-chat>=0.82.0
Dynamic: author
Dynamic: requires-python
